srtify/__init__.py
srtify/__main__.py
srtify/cli/__init__.py
srtify/cli/cli_handler.py
srtify/cli/commands.py
srtify/cli/menu.py
srtify/cli/settings_commands.py
srtify/core/__init__.py
srtify/core/file_encoding.py
srtify/core/prompts.py
srtify/core/settings.py
srtify/core/translator.py
srtify/models/__init__.py
srtify/models/application.py
srtify/models/config.py
srtify/models/prompt_library.py
srtify/models/translation.py
srtify/utils/__init__.py
srtify/utils/exceptions.py
srtify/utils/log.py
srtify/utils/paths.py
srtify/utils/utils.py
srtify-0.1.4.dist-info/licenses/LICENSE
srtify-0.1.4.dist-info/METADATA
srtify-0.1.4.dist-info/WHEEL
srtify-0.1.4.dist-info/entry_points.txt
srtify-0.1.4.dist-info/top_level.txt
srtify-0.1.4.dist-info/RECORD
