Metadata-Version: 2.4
Name: srtify
Version: 0.1.4
Summary: CLI tool for translating SRT files using Gemini AI
Author-email: Hirad <hirad@hirad.it>
License: GNU GENERAL PUBLIC LICENSE
Project-URL: Homepage, https://git.hirad.it/Hirad/Srtify
Project-URL: Documentation, https://git.hirad.it/Hirad/Srtify
Project-URL: Repository, https://git.hirad.it/Hirad/Srtify
Keywords: srt,subtitles,translation,gemini,ai
Classifier: Development Status :: 4 - Beta
Classifier: Intended Audience :: End Users/Desktop
Classifier: License :: OSI Approved :: GNU General Public License v3 or later (GPLv3+)
Classifier: Programming Language :: Python :: 3.12
Classifier: Topic :: Text Processing :: Linguistic
Requires-Python: >=3.12
License-File: LICENSE
Requires-Dist: chardet>=5.2.0
Requires-Dist: click>=8.2.1
Requires-Dist: colorlog>=6.9.0
Requires-Dist: gemini-srt-translator>=2.1.3
Requires-Dist: platformdirs>=4.3.8
Requires-Dist: setuptools>=65.5.1
Requires-Dist: simple-term-menu>=1.6.6
Requires-Dist: types-click>=7.1.8
Requires-Dist: wheel>=0.45.1
Provides-Extra: dev
Requires-Dist: black>=25.1.0; extra == "dev"
Requires-Dist: pylint>=3.3.8; extra == "dev"
Requires-Dist: ruff>=0.12.9; extra == "dev"
Dynamic: license-file
